solar_crypto/__init__.py
solar_crypto/constants.py
solar_crypto/exceptions.py
solar_crypto/configuration/__init__.py
solar_crypto/configuration/fee.py
solar_crypto/configuration/network.py
solar_crypto/identity/__init__.py
solar_crypto/identity/address.py
solar_crypto/identity/private_key.py
solar_crypto/identity/public_key.py
solar_crypto/identity/wif.py
solar_crypto/networks/__init__.py
solar_crypto/networks/mainnet.py
solar_crypto/networks/testnet.py
solar_crypto/schnorr/__init__.py
solar_crypto/schnorr/schnorr.py
solar_crypto/transactions/__init__.py
solar_crypto/transactions/deserializer.py
solar_crypto/transactions/serializer.py
solar_crypto/transactions/transaction.py
solar_crypto/transactions/builder/__init__.py
solar_crypto/transactions/builder/base.py
solar_crypto/transactions/builder/burn.py
solar_crypto/transactions/builder/delegate_registration.py
solar_crypto/transactions/builder/delegate_resignation.py
solar_crypto/transactions/builder/htlc_claim.py
solar_crypto/transactions/builder/htlc_lock.py
solar_crypto/transactions/builder/htlc_refund.py
solar_crypto/transactions/builder/ipfs.py
solar_crypto/transactions/builder/legacy_transfer.py
solar_crypto/transactions/builder/legacy_vote.py
solar_crypto/transactions/builder/multi_signature_registration.py
solar_crypto/transactions/builder/second_signature_registration.py
solar_crypto/transactions/builder/transfer.py
solar_crypto/transactions/builder/vote.py
solar_crypto/transactions/deserializers/__init__.py
solar_crypto/transactions/deserializers/base.py
solar_crypto/transactions/deserializers/burn.py
solar_crypto/transactions/deserializers/delegate_registration.py
solar_crypto/transactions/deserializers/delegate_resignation.py
solar_crypto/transactions/deserializers/htlc_claim.py
solar_crypto/transactions/deserializers/htlc_lock.py
solar_crypto/transactions/deserializers/htlc_refund.py
solar_crypto/transactions/deserializers/ipfs.py
solar_crypto/transactions/deserializers/legacy_transfer.py
solar_crypto-3.1.0.dist-info/LICENSE
solar_crypto-3.1.0.dist-info/METADATA
solar_crypto-3.1.0.dist-info/WHEEL
solar_crypto-3.1.0.dist-info/top_level.txt
solar_crypto-3.1.0.dist-info/RECORD
