Metadata-Version: 2.1
Name: solar-crypto
Version: 3.1.0
Summary: A simple Cryptography Implementation in Python for the Solar Blockchain.
Home-page: https://github.com/Solar-network/python-crypto
Author: Solar-Network
Author-email: hello@solar.org
Requires-Python: >=3.6
License-File: LICENSE
Requires-Dist: base58
Requires-Dist: binary-helpers
Requires-Dist: coincurve
Requires-Dist: btclib
Requires-Dist: pycryptodome
Provides-Extra: dev
Requires-Dist: base58 ; extra == 'dev'
Requires-Dist: binary-helpers ; extra == 'dev'
Requires-Dist: coincurve ; extra == 'dev'
Requires-Dist: btclib ; extra == 'dev'
Requires-Dist: pycryptodome ; extra == 'dev'
Requires-Dist: flake8 (==4.0.1) ; extra == 'dev'
Requires-Dist: flake8-import-order (==0.18.1) ; extra == 'dev'
Requires-Dist: flake8-print (==4.0.1) ; extra == 'dev'
Requires-Dist: flake8-quotes (==3.3.1) ; extra == 'dev'
Requires-Dist: isort (==5.10.1) ; extra == 'dev'
Requires-Dist: pytest-cov (==2.5.1) ; extra == 'dev'
Requires-Dist: black (==22.3.0) ; extra == 'dev'
Requires-Dist: build (==0.8.0) ; extra == 'dev'
Requires-Dist: twine (==3.8.0) ; extra == 'dev'
Requires-Dist: pytest (==7.0.1) ; (python_version < "3.7") and extra == 'dev'
Requires-Dist: pytest (==7.1.2) ; (python_version >= "3.7") and extra == 'dev'
Provides-Extra: test
Requires-Dist: flake8 (==4.0.1) ; extra == 'test'
Requires-Dist: flake8-import-order (==0.18.1) ; extra == 'test'
Requires-Dist: flake8-print (==4.0.1) ; extra == 'test'
Requires-Dist: flake8-quotes (==3.3.1) ; extra == 'test'
Requires-Dist: isort (==5.10.1) ; extra == 'test'
Requires-Dist: pytest-cov (==2.5.1) ; extra == 'test'
Requires-Dist: black (==22.3.0) ; extra == 'test'
Requires-Dist: build (==0.8.0) ; extra == 'test'
Requires-Dist: twine (==3.8.0) ; extra == 'test'
Requires-Dist: pytest (==7.0.1) ; (python_version < "3.7") and extra == 'test'
Requires-Dist: pytest (==7.1.2) ; (python_version >= "3.7") and extra == 'test'
